vanqc/__init__.py
vanqc/cli/__init__.py
vanqc/cli/main.py
vanqc/task/__init__.py
vanqc/task/bcftools.py
vanqc/task/core.py
vanqc/task/gatk.py
vanqc/task/picard.py
vanqc/task/snpeff.py
vanqc/task/vep.py
vanqc-0.1.0.dist-info/LICENSE
vanqc-0.1.0.dist-info/METADATA
vanqc-0.1.0.dist-info/WHEEL
vanqc-0.1.0.dist-info/entry_points.txt
vanqc-0.1.0.dist-info/top_level.txt
vanqc-0.1.0.dist-info/RECORD
