Metadata-Version: 2.1
Name: vanqc
Version: 0.1.0
Summary: Variant Annotator and QC Checker for Human Genome Sequencing
Home-page: https://github.com/dceoy/vanqc.git
Author: Daichi Narushima
Author-email: dnarsil+github@gmail.com
License: UNKNOWN
Platform: UNKNOWN
Classifier: Development Status :: 4 - Beta
Classifier: Environment :: Console
Classifier: License :: OSI Approved :: MIT License
Classifier: Operating System :: POSIX :: Linux
Classifier: Operating System :: MacOS
Classifier: Programming Language :: Python :: 3
Classifier: Topic :: Scientific/Engineering :: Bio-Informatics
Requires-Python: >=3.6
Requires-Dist: docopt
Requires-Dist: ftarc
Requires-Dist: luigi
Requires-Dist: psutil
